plumial/__init__.py
plumial/types.py
plumial/core/D.py
plumial/core/P.py
plumial/core/__init__.py
plumial/core/basis.py
plumial/utils/__init__.py
plumial/utils/binary.py
plumial/utils/functions.py
plumial/utils/matrix_utils.py
plumial/utils/symbolic.py
plumial-0.1.0.dist-info/licenses/LICENSE
plumial-0.1.0.dist-info/METADATA
plumial-0.1.0.dist-info/WHEEL
plumial-0.1.0.dist-info/top_level.txt
plumial-0.1.0.dist-info/RECORD
