Metadata-Version: 2.4
Name: plumial
Version: 0.1.0
Summary: A Python package for exploring cyclic structures in polynomial rings
Author-email: Jon Seymour <jon@wildducktheories.com>
Maintainer-email: Jon Seymour <jon@wuldducktheories.com>
License: MIT
Project-URL: Homepage, https://github.com/wildducktheories/plumial
Project-URL: Repository, https://github.com/wildducktheories/plumial
Project-URL: Documentation, https://plumial.readthedocs.io
Project-URL: Bug Tracker, https://github.com/wildducktheories/plumial/issues
Keywords: collatz,conjecture,mathematics,number-theory
Classifier: Development Status :: 3 - Alpha
Classifier: Intended Audience :: Science/Research
Classifier: License :: OSI Approved :: MIT License
Classifier: Operating System :: OS Independent
Classifier: Programming Language :: Python :: 3
Classifier: Programming Language :: Python :: 3.8
Classifier: Programming Language :: Python :: 3.9
Classifier: Programming Language :: Python :: 3.10
Classifier: Programming Language :: Python :: 3.11
Classifier: Programming Language :: Python :: 3.12
Classifier: Topic :: Scientific/Engineering :: Mathematics
Requires-Python: >=3.8
License-File: LICENSE
Requires-Dist: sympy
Requires-Dist: numpy
Provides-Extra: dev
Requires-Dist: pytest>=7.0; extra == "dev"
Requires-Dist: pytest-cov>=4.0; extra == "dev"
Requires-Dist: black>=22.0; extra == "dev"
Requires-Dist: isort>=5.0; extra == "dev"
Requires-Dist: flake8>=5.0; extra == "dev"
Requires-Dist: mypy>=1.0; extra == "dev"
Requires-Dist: pre-commit>=2.0; extra == "dev"
Requires-Dist: jupyter; extra == "dev"
Provides-Extra: docs
Requires-Dist: sphinx>=5.0; extra == "docs"
Requires-Dist: sphinx-rtd-theme>=1.0; extra == "docs"
Dynamic: license-file
